openpyutils/__init__.py
openpyutils/csv.py
openpyutils/logger.py
openpyutils-0.0.1.dist-info/licenses/LICENSE
openpyutils-0.0.1.dist-info/METADATA
openpyutils-0.0.1.dist-info/WHEEL
openpyutils-0.0.1.dist-info/top_level.txt
openpyutils-0.0.1.dist-info/RECORD
